pthelper/device.py
pthelper/metrics.py
pthelper/model.py
torch_helper-0.5.1a0.dist-info/LICENSE
torch_helper-0.5.1a0.dist-info/METADATA
torch_helper-0.5.1a0.dist-info/WHEEL
torch_helper-0.5.1a0.dist-info/top_level.txt
torch_helper-0.5.1a0.dist-info/RECORD
