Metadata-Version: 2.1
Name: torch-helper
Version: 0.5.1a0
Summary: A pytorch library to provide some common utility functions.
Home-page: https://github.com/santanu94/torch-helper.git
Author: Santanu Bhattacharjee
Author-email: mail.santanu94@gmail.com
License: UNKNOWN
Keywords: PyTorch,Deep Learning
Platform: UNKNOWN
Classifier: Programming Language :: Python :: 3
Classifier: License :: OSI Approved :: MIT License
Classifier: Operating System :: OS Independent
Requires-Python: >=3.6
Requires-Dist: torch (>=1.0.0)
Requires-Dist: sklearn
